[
    {
      "Course ID": 50275,
      "Course Name": "C S 323E ELEMENTS OF SCIENTIF COMPUTING",
      "Day": "M W",
      "Hour": "3:30 - 5:00 pm",
      "Room": "RLP 0.502",
      "Instruction Mode": "Face-to-face",
      "Instructor Name": "MITRA, SHYAMAL K",
      "Status": "waitlisted",
      "Flags": ""
    },
    {
      "Course ID": 50280,
      "Course Name": "C S 324E ELEM OF GRAPHICS/VISUALIZATN",
      "Day": "M W F",
      "Hour": "1:00 - 2:00 pm",
      "Room": "GDC 5.302",
      "Instruction Mode": "Face-to-face",
      "Instructor Name": "ABRAHAM, SARAH ANNE",
      "Status": "waitlisted",
      "Flags": ""
    },
    {
      "Course ID": 50285,
      "Course Name": "C S 326E ELEMENTS OF NETWORKING",
      "Day": "T TH",
      "Hour": "11:00 a.m.-12:30 p.m.",
      "Room": "GDC 5.302",
      "Instruction Mode": "Face-to-face",
      "Instructor Name": "HAN, MIKYUNG",
      "Status": "waitlisted",
      "Flags": ""
    },
    {
      "Course ID": 50290,
      "Course Name": "C S 326E ELEMENTS OF NETWORKING",
      "Day": "T TH",
      "Hour": "12:30 p.m.-2:00 p.m.",
      "Room": "JGB 2.218",
      "Instruction Mode": "Face-to-face",
      "Instructor Name": "HAN, MIKYUNG",
      "Status": "waitlisted",
      "Flags": ""
    },
    {
      "Course ID": 50295,
      "Course Name": "C S 327E ELEMENTS OF DATABASES",
      "Day": "M W F",
      "Hour": "10:00 a.m.-11:00 a.m.",
      "Room": "JGB 2.218",
      "Instruction Mode": "Face-to-face",
      "Instructor Name": "PALACIOS, JOAQUIN MARCOS",
      "Status": "waitlisted",
      "Flags": ""
    },
    {
      "Course ID": 50300,
      "Course Name": "C S 327E ELEMENTS OF DATABASES",
      "Day": "M W F",
      "Hour": "1:00 p.m.-2:00 p.m.",
      "Room": "JGB 2.218",
      "Instruction Mode": "Face-to-face",
      "Instructor Name": "PALACIOS, JOAQUIN MARCOS",
      "Status": "waitlisted",
      "Flags": ""
    },
    {
      "Course ID": 50305,
      "Course Name": "C S 327E ELEMENTS OF DATABASES",
      "Day": "F",
      "Hour": "2:00 p.m.-5:00 p.m.",
      "Room": "",
      "Instruction Mode": "Hybrid or Blended",
      "Instructor Name": "COHEN, SHIRLEY",
      "Status": "canceled",
      "Flags": ""
    },
    {
      "Course ID": 50308,
      "Course Name": "C S 327E ELEMENTS OF DATABASES",
      "Day": "T TH",
      "Hour": "12:30 p.m.-2:00 p.m.",
      "Room": "UTC 1.104",
      "Instruction Mode": "Face-to-face",
      "Instructor Name": "JOSHI, PRASHANT D",
      "Status": "waitlisted",
      "Flags": ""
    },
    {
      "Course ID": 50309,
      "Course Name": "C S 327E ELEMENTS OF DATABASES",
      "Day": "T TH",
      "Hour": "9:30 a.m.-11:00 a.m.",
      "Room": "RLP 1.104",
      "Instruction Mode": "Face-to-face",
      "Instructor Name": "JOSHI, PRASHANT D",
      "Status": "waitlisted",
      "Flags": ""
    }
  ]
  